{"course_name": "General Physics: Mechanics and Particle Dynamics", "course_number": "PHYS161", "credits": "3", "grading_method": "Reg, P-F, Aud,", "prereq": "MATH141", "description": "First semester of a three-semester calculus-based general physics course. Laws of motion, force, and energy; principles of mechanics, collisions, linear momentum, rotation, and gravitation.", "geneds": ["DSNS", "DSNL                                    (if taken with PHYS275)"], "sections": [{"section_id": "0101", "professor": "David Buehrle", "total_seats": "32", "open_seats": "30", "waitlist": "0", "times": "MWF 3:00pm-3:50pm | Tu 3:00pm-3:50pm"}, {"section_id": "0104", "professor": "David Buehrle", "total_seats": "32", "open_seats": "26", "waitlist": "0", "times": "MWF 3:00pm-3:50pm | F 11:00am-11:50am"}, {"section_id": "0201", "professor": "Instructor: TBA", "total_seats": "32", "open_seats": "31", "waitlist": "0", "times": "TuTh 11:00am-12:15pm | Th 8:00am-8:50am"}, {"section_id": "0202", "professor": "Instructor: TBA", "total_seats": "32", "open_seats": "28", "waitlist": "0", "times": "TuTh 11:00am-12:15pm | Tu 2:00pm-2:50pm"}, {"section_id": "0203", "professor": "Instructor: TBA", "total_seats": "32", "open_seats": "30", "waitlist": "0", "times": "TuTh 11:00am-12:15pm | W 3:00pm-3:50pm"}, {"section_id": "0204", "professor": "Instructor: TBA", "total_seats": "32", "open_seats": "32", "waitlist": "0", "times": "TuTh 11:00am-12:15pm | M 4:00pm-4:50pm"}, {"section_id": "0301", "professor": "Alberto Belloni", "total_seats": "32", "open_seats": "30", "waitlist": "0", "times": "MWF 10:00am-10:50am | Th 3:00pm-3:50pm"}, {"section_id": "0302", "professor": "Alberto Belloni", "total_seats": "32", "open_seats": "29", "waitlist": "0", "times": "MWF 10:00am-10:50am | Tu 4:00pm-4:50pm"}, {"section_id": "0303", "professor": "Alberto Belloni", "total_seats": "32", "open_seats": "23", "waitlist": "0", "times": "MWF 10:00am-10:50am | W 12:00pm-12:50pm"}, {"section_id": "0304", "professor": "Alberto Belloni", "total_seats": "32", "open_seats": "32", "waitlist": "0", "times": "MWF 10:00am-10:50am | W 3:00pm-3:50pm"}, {"section_id": "FC01", "professor": "Aria Heidarian", "total_seats": "26", "open_seats": "13", "waitlist": "0", "times": "TuTh 6:00pm-7:15pm"}]}