{"course_name": "Advanced Composition", "course_number": "ENGL391", "sections": [{"section_id": "0401", "professor": "Mark Forrester", "locations": "TWS 1321", "times": "MWF 12:00pm-12:50pm"}, {"section_id": "0402", "professor": "Catherine Byrne", "locations": "LEF 1221", "times": "MWF 12:00pm-12:50pm"}, {"section_id": "0501", "professor": "Catherine Byrne", "locations": "KEY 0121", "times": "MWF 1:00pm-1:50pm"}, {"section_id": "0601", "professor": "Catherine Byrne", "locations": "TWS 3250", "times": "MW 2:00pm-3:15pm"}, {"section_id": "0701", "professor": "Anna Josephson", "locations": "KEY 0124", "times": "MW 3:30pm-4:45pm"}, {"section_id": "0801", "professor": "Catherine Byrne", "locations": "JMZ 2122", "times": "MW 5:00pm-6:15pm"}, {"section_id": "0901", "professor": "Anna Josephson", "locations": "ASY 3221", "times": "MW 6:30pm-7:45pm"}, {"section_id": "1101", "professor": "Christopher Crane", "locations": "JMZ 0125", "times": "TuTh 9:30am-10:45am"}, {"section_id": "1201", "professor": "John Kim", "locations": "TWS 3136", "times": "TuTh 11:00am-12:15pm"}, {"section_id": "1301", "professor": "Christopher Crane", "locations": "TWS 1105", "times": "TuTh 12:30pm-1:45pm"}, {"section_id": "1505", "professor": "Olubukola Salako", "locations": "KNI 1206", "times": "TuTh 5:00pm-6:15pm"}, {"section_id": "1701", "professor": "Instructor: TBA", "locations": "TWS 1105", "times": "Tu 6:30pm-9:10pm"}, {"section_id": "1901", "professor": "Mark Fitzgerald", "locations": "TWS 0232", "times": "Th 6:30pm-9:10pm"}, {"section_id": "0201", "professor": "Mark Forrester", "locations": "EDU 3233", "times": "MWF 10:00am-10:50am"}]}