{"course_name": "Oral Communication", "course_number": "INAG110", "sections": [{"section_id": "0101", "professor": "Eric Dunning", "locations": "EGR 1110", "times": "MWF 8:00am-8:50am"}, {"section_id": "0201", "professor": "Chelsea Mays-Williams", "locations": "ATL 1410", "times": "MWF 8:00am-8:50am"}, {"section_id": "0301", "professor": "Eric Dunning", "locations": "EGR 1110", "times": "MWF 9:00am-9:50am"}, {"section_id": "0401", "professor": "Robert Ballenger", "locations": "ATL 2316", "times": "MWF 9:00am-9:50am"}, {"section_id": "0501", "professor": "Chelsea Mays-Williams", "locations": "ATL 1410", "times": "MWF 9:00am-9:50am"}, {"section_id": "0701", "professor": "Chelsea Mays-Williams", "locations": "ATL 1410", "times": "MWF 10:00am-10:50am"}, {"section_id": "0801", "professor": "Lori Sefton", "locations": "EGR 3102", "times": "MWF 10:00am-10:50am"}, {"section_id": "0901", "professor": "Eric Dunning", "locations": "EGR 1102", "times": "MWF 11:00am-11:50am"}, {"section_id": "1001", "professor": "Lori Sefton", "locations": "EGR 3114", "times": "MWF 11:00am-11:50am"}, {"section_id": "1101", "professor": "Robert Ballenger", "locations": "ATL 2316", "times": "MWF 11:00am-11:50am"}, {"section_id": "1201", "professor": "George Kurtzweil", "locations": "CHE 2140", "times": "MWF 12:00pm-12:50pm"}, {"section_id": "1301", "professor": "Lori Sefton", "locations": "EGR 3114", "times": "MWF 12:00pm-12:50pm"}, {"section_id": "1401", "professor": "David Gormong", "locations": "EGR 1102", "times": "MWF 12:00pm-12:50pm"}, {"section_id": "1501", "professor": "David Gormong", "locations": "EGR 1102", "times": "MWF 1:00pm-1:50pm"}, {"section_id": "1701", "professor": "George Kurtzweil", "locations": "CHE 2140", "times": "MWF 1:00pm-1:50pm"}, {"section_id": "1801", "professor": "David Gormong", "locations": "EGR 1102", "times": "MWF 2:00pm-2:50pm"}, {"section_id": "1901", "professor": "George Kurtzweil", "locations": "CHE 2140", "times": "MWF 2:00pm-2:50pm"}, {"section_id": "2201", "professor": "Samuel Rubin", "locations": "PLS 1164", "times": "M 6:00pm-8:45pm"}, {"section_id": "2301", "professor": "Samuel Rubin", "locations": "PLS 1164", "times": "W 6:00pm-8:45pm"}, {"section_id": "2401", "professor": "Chelsea Mays-Williams", "locations": "ATL 1410", "times": "TuTh 8:00am-9:15am"}, {"section_id": "2501", "professor": "Eric Dunning", "locations": "PLS 1162", "times": "TuTh 8:00am-9:15am"}, {"section_id": "2601", "professor": "Chelsea Mays-Williams", "locations": "ATL 1410", "times": "TuTh 9:30am-10:45am"}, {"section_id": "2801", "professor": "Lori Sefton", "locations": "PLS 1172", "times": "TuTh 9:30am-10:45am"}, {"section_id": "2901", "professor": "Lori Sefton", "locations": "PLS 1172", "times": "TuTh 11:00am-12:15pm"}, {"section_id": "3001", "professor": "David Gormong", "locations": "JMZ 2206", "times": "TuTh 11:00am-12:15pm"}, {"section_id": "3101", "professor": "Robert Ballenger", "locations": "ARC 1125", "times": "TuTh 11:00am-12:15pm"}, {"section_id": "3201", "professor": "Robert Ballenger", "locations": "ARC 1125", "times": "TuTh 12:30pm-1:45pm"}, {"section_id": "3301", "professor": "George Kurtzweil", "locations": "CHE 2140", "times": "TuTh 12:30pm-1:45pm"}, {"section_id": "3401", "professor": "David Gormong", "locations": "JMZ 2206", "times": "TuTh 12:30pm-1:45pm"}, {"section_id": "3501", "professor": "George Kurtzweil", "locations": "CHE 2140", "times": "TuTh 2:00pm-3:15pm"}, {"section_id": "3701", "professor": "Samuel Rubin", "locations": "EGR 3102", "times": "TuTh 2:00pm-3:15pm"}, {"section_id": "3801", "professor": "Samuel Rubin", "locations": "EGR 3102", "times": "TuTh 3:30pm-4:45pm"}, {"section_id": "4001", "professor": "Samuel Rubin", "locations": "EGR 3102", "times": "TuTh 5:00pm-6:15pm"}, {"section_id": "0601", "professor": "Robert Ballenger", "locations": "ATL 0201", "times": "MWF 10:00am-10:50am"}]}