{"course_name": "Oral Communication: Principles and Practices", "course_number": "COMM107B", "credits": "3", "grading_method": "Reg, P-F,", "description": "A study of and practice in oral communication, including principles of interviewing, group discussion, listening, informative briefings, and persuasive speeches.", "geneds": ["FSOC"], "sections": [{"section_id": "0101", "professor": "Melissa Lucas", "total_seats": "19", "open_seats": "19", "waitlist": "0", "times": "TuTh 12:30pm-1:45pm"}, {"section_id": "0201", "professor": "Christine Schaaf", "total_seats": "19", "open_seats": "19", "waitlist": "0", "times": "TuTh 12:30pm-1:45pm"}]}