{"average_gpa": null, "professors": ["Hoda Mahmoudi"], "reviews": [], "department": "BSOS", "course_number": "240", "name": "BSOS240", "title": "The Problem of Prejudice: Overcoming Impediments to Global Peace and Justice", "credits": 3, "description": "What is prejudice? How are our prejudices formed? What similarities and differences are there between various forms of prejudice across race, gender, nationality, politics, religion, among others? What is the relationship between prejudice and conflict? What is the role of prejudice in thinking about issues of peace and justice? How can we better understand the role that prejudice and discrimination have in a globalizing world? What can we learn from a scientific basis of knowledge about the causes of prejudice? This course will survey interdisciplinary scholarly research and popular cultural conversations about the root causes of prejudice and discrimination. You are expected to examine empirical evidence toward formulating your own views about the impact that all forms of prejudice impose on the human condition and the role it has played in your own life. Based on research evidence, the course encourages the search for solutions to the blight of prejudice.", "is_recent": true, "geneds": null}