{"average_gpa": 3.7047619047619045, "professors": ["Larisa Cioaca", "Shala Larson", "Heather McHale", "Eric Dunning"], "reviews": [], "department": "INAG", "course_number": "252", "name": "INAG252", "title": "Agricultural Public Relations", "credits": 3, "description": "<b>Recommended:</b> INAG103.\nIntroduces the fundamental concepts and procedures of public relations in agriculture. Topics include understanding external audiences; key practices in agricultural media relations, social media, executive communication, and crisis communication; and managing the research, planning, and evaluation aspects of the public relations process. Students will gain the public relations knowledge and skills necessary for communicating effectively with an organization's external audiences.", "is_recent": true, "geneds": null}