{"course_name": "Introduction American Studies", "course_number": "AMST101", "credits": "3", "grading_method": "Reg, P-F, Aud,", "description": "Introduces students to the interdisciplinary field of American Studies by examining concepts such as culture, identity, cultural practices, and globalization, as well as theories underlying these concepts. Engages key themes, especially constructions of difference and identity, cultures of everyday life, and America and the world.", "geneds": ["DSHU", "DVUP"], "sections": [{"section_id": "0101", "professor": "Christina Hanhardt", "total_seats": "4", "open_seats": "1", "waitlist": "0", "times": "MW 11:00am-11:50am | F 10:00am-10:50am"}, {"section_id": "0102", "professor": "Christina Hanhardt", "total_seats": "4", "open_seats": "1", "waitlist": "0", "times": "MW 11:00am-11:50am | F 11:00am-11:50am"}, {"section_id": "0103", "professor": "Christina Hanhardt", "total_seats": "4", "open_seats": "1", "waitlist": "0", "times": "MW 11:00am-11:50am | F 11:00am-11:50am"}, {"section_id": "0104", "professor": "Christina Hanhardt", "total_seats": "4", "open_seats": "0", "waitlist": "0", "times": "MW 11:00am-11:50am | F 12:00pm-12:50pm"}]}