{"course_name": "Leadership and Ethnicity", "course_number": "HESI423", "credits": "3", "grading_method": "Reg, P-F, Aud,", "description": "Examines the concept of leadership from the standpoint of race, ethnicity, and culture. Specifically, we will explore the concept and differing meanings of leader and leadership within racial/ethnic communities in the United States. Issues of leaders and leadership will be examined as influenced by political, cultural, and historic events. The course will place particular emphasis on colleges and universities as a microcosm of the larger society and as a cultural site for exploring and assessing issues of race, ethnicity, diversity and leadership.", "geneds": ["DVCC"], "sections": [{"section_id": "0101", "professor": "Brandon Dula", "total_seats": "25", "open_seats": "19", "waitlist": "0", "times": "TuTh 2:00pm-3:15pm"}]}