{"course_name": "Calculus I", "course_number": "MATH140H", "credits": "4", "grading_method": "Reg, P-F, Aud,", "prereq": "MATH115", "description": "Introduction to calculus, including functions, limits, continuity, derivatives and applications of the derivative, sketching of graphs of functions, definite and indefinite integrals, and calculation of area. The course is especially recommended for science, engineering and mathematics majors.", "geneds": ["FSAR", "FSMA"], "sections": [{"section_id": "0101", "professor": "Shiferaw Berhanu", "total_seats": "22", "open_seats": "22", "waitlist": "0", "times": "MF 10:00am-10:50am | W 10:00am-11:50am"}, {"section_id": "0201", "professor": "Instructor: TBA", "total_seats": "22", "open_seats": "22", "waitlist": "0", "times": "WF 11:00am-11:50am | M 11:00am-12:50pm"}]}