{"course_name": "Introduction to Computer Programming via the Web", "course_number": "CMSC122", "credits": "3", "grading_method": "Reg,", "restriction": "Must not have completed any courses from CMSC131-499 course range; and must not be concurrently enrolled in CMSC131", "description": "Introduction to computer programming in the context of developing full featured dynamic web sites. Uses a problem solving approach to teach basics of program design and implementation using JavaScript; relates these skills to creation of dynamic web sites; then explores both the potential and limits of web-based information sources for use in research. Intended to help relate a student's major to these emerging technologies.", "geneds": ["DSSP"], "sections": [{"section_id": "0101", "professor": "Pedram Sadeghian", "total_seats": "95", "open_seats": "89", "waitlist": "0", "times": "MWF 1:00pm-1:50pm"}, {"section_id": "FC01", "professor": "Jennifer Manly", "total_seats": "64", "open_seats": "57", "waitlist": "0", "times": "TuTh 4:30pm-5:45pm"}]}